{"Year": "1980", "Poster": "https://m.media-amazon.com/images/M/MV5BMWE0MThhNGQtZmFmNS00NTliLWFiZDgtNmE1MTQyNmVmNzQ5XkEyXkFqcGdeQXVyNjc1NTYyMjg@._V1_SX300.jpg", "Website": "N/A", "Language": "English, Afrikaans, Ungwatsi", "Released": "26 Oct 1984", "Production": "20th Century Fox Film Corporat", "Rated": "PG", "Response": "True", "Genre": "Comedy", "BoxOffice": "N/A", "Type": "movie", "Runtime": "109 min", "DVD": "01 Jun 2004", "Country": "Botswana, South Africa", "Plot": "A comic allegory about a traveling Bushman who encounters modern civilization and its stranger aspects, including a clumsy scientist and a band of revolutionaries.", "Ratings": [{"Source": "Internet Movie Database", "Value": "7.3/10"}, {"Source": "Rotten Tomatoes", "Value": "95%"}, {"Source": "Metacritic", "Value": "73/100"}], "Writer": "Jamie Uys", "Title": "The Gods Must Be Crazy", "Awards": "2 wins & 3 nominations.", "imdbRating": "7.3", "Director": "Jamie Uys", "imdbID": "tt0080801", "Actors": "Marius Weyers, Sandra Prinsloo, N!xau, Louw Verwey", "Metascore": "73", "imdbVotes": "47,324"}