{"Plot": "The story of the final Emperor of China.", "Response": "True", "Awards": "Won 9 Oscars. Another 47 wins & 16 nominations.", "Ratings": [{"Source": "Internet Movie Database", "Value": "7.8/10"}, {"Source": "Rotten Tomatoes", "Value": "92%"}, {"Source": "Metacritic", "Value": "76/100"}], "imdbID": "tt0093389", "Country": "UK, Italy, China, France, USA", "Writer": "Mark Peploe (screenplay), Bernardo Bertolucci (screenplay), Enzo Ungari (initial screenplay collaboration)", "Website": "N/A", "Year": "1987", "Director": "Bernardo Bertolucci", "Released": "15 Apr 1988", "DVD": "20 Mar 2001", "BoxOffice": "N/A", "Actors": "John Lone, Joan Chen, Peter O'Toole, Ruocheng Ying", "Genre": "Biography, Drama, History", "Production": "Columbia Pictures", "Runtime": "163 min", "Title": "The Last Emperor", "Rated": "PG-13", "Type": "movie", "Metascore": "76", "imdbVotes": "80,306", "Language": "English, Mandarin, Japanese", "Poster": "https://m.media-amazon.com/images/M/MV5BZTk0NDU4YmItOTk0ZS00ODc2LTkwNGItNWI5MDJkNTJiYWMxXkEyXkFqcGdeQXVyNjUwNzk3NDc@._V1_SX300.jpg", "imdbRating": "7.8"}