{"BoxOffice": "N/A", "Website": "http://www.theofficialjohncarpenter.com/pages/themovies/th/th.html", "imdbVotes": "310,049", "Ratings": [{"Value": "8.1/10", "Source": "Internet Movie Database"}, {"Value": "83%", "Source": "Rotten Tomatoes"}, {"Value": "57/100", "Source": "Metacritic"}], "Country": "USA", "Poster": "https://m.media-amazon.com/images/M/MV5BNDcyZmFjY2YtN2I1OC00MzU3LWIzZGEtZDA5N2VlNDJjYWI3L2ltYWdlXkEyXkFqcGdeQXVyNTAyODkwOQ@@._V1_SX300.jpg", "Language": "English, Norwegian", "Actors": "Kurt Russell, Wilford Brimley, T.K. Carter, David Clennon", "imdbID": "tt0084787", "Runtime": "109 min", "Released": "25 Jun 1982", "Rated": "R", "Response": "True", "Production": "Universal Pictures", "imdbRating": "8.1", "Type": "movie", "Metascore": "57", "Writer": "Bill Lancaster (screenplay), John W. Campbell Jr. (story)", "Title": "The Thing", "Year": "1982", "Plot": "A crew in Antarctica finds a neighboring camp destroyed and its crew dead. Whatever killed them is nowhere to be found, unless it's hidden in plain sight.", "Genre": "Horror, Mystery, Sci-Fi", "Director": "John Carpenter", "DVD": "28 Aug 2001", "Awards": "3 nominations."}