{"Language": "English", "Runtime": "106 min", "Production": "HBO Video", "imdbID": "tt0091828", "Year": "1986", "Genre": "Action, Crime, Thriller", "Ratings": [{"Source": "Internet Movie Database", "Value": "5.5/10"}, {"Source": "Rotten Tomatoes", "Value": "25%"}, {"Source": "Metacritic", "Value": "44/100"}], "DVD": "13 Oct 1998", "imdbRating": "5.5", "Response": "True", "Type": "movie", "BoxOffice": "N/A", "Released": "06 Jun 1986", "Website": "N/A", "Rated": "R", "Plot": "A former FBI agent turned small-town sheriff agrees to help the FBI chief infiltrate the Chicago mafia when the FBI chief's son is killed by them.", "Awards": "N/A", "Poster": "https://m.media-amazon.com/images/M/MV5BYTVkNWIwZmYtMzM5MS00ZTcwLWI0ZjEtNTVlMTNjZWViNzliXkEyXkFqcGdeQXVyNTIzOTk5ODM@._V1_SX300.jpg", "Title": "Raw Deal", "Writer": "Luciano Vincenzoni (story), Sergio Donati (story), Gary DeVore (screenplay), Norman Wexler (screenplay)", "Country": "USA, Netherlands", "Metascore": "44", "Actors": "Arnold Schwarzenegger, Kathryn Harrold, Sam Wanamaker, Paul Shenar", "Director": "John Irvin", "imdbVotes": "26,127"}