{"Year": "1989", "Poster": "https://m.media-amazon.com/images/M/MV5BMjE0ODEwNjM2NF5BMl5BanBnXkFtZTcwMjU2Mzg3NA@@._V1_SX300.jpg", "Website": "N/A", "Language": "English", "Released": "21 Jul 1989", "Production": "Columbia Pictures", "Rated": "R", "Response": "True", "Genre": "Comedy, Drama, Romance", "BoxOffice": "N/A", "Type": "movie", "Runtime": "96 min", "DVD": "13 Oct 1998", "Country": "USA", "Plot": "Harry and Sally have known each other for years, and are very good friends, but they fear sex would ruin the friendship.", "Ratings": [{"Source": "Internet Movie Database", "Value": "7.6/10"}, {"Source": "Rotten Tomatoes", "Value": "90%"}, {"Source": "Metacritic", "Value": "76/100"}], "Writer": "Nora Ephron", "Title": "When Harry Met Sally...", "Awards": "Nominated for 1 Oscar. Another 4 wins & 16 nominations.", "imdbRating": "7.6", "Director": "Rob Reiner", "imdbID": "tt0098635", "Actors": "Billy Crystal, Meg Ryan, Carrie Fisher, Bruno Kirby", "Metascore": "76", "imdbVotes": "168,740"}