{"Plot": "A group of seven former college friends gather for a weekend reunion at a South Carolina winter house after the funeral of one of their friends.", "Country": "USA", "Response": "True", "Year": "1983", "BoxOffice": "N/A", "imdbRating": "7.2", "Director": "Lawrence Kasdan", "Type": "movie", "Production": "Columbia Pictures", "Rated": "R", "Website": "N/A", "Poster": "https://m.media-amazon.com/images/M/MV5BMTA4MjEyMTk5NzheQTJeQWpwZ15BbWU4MDY1NDA1MTAx._V1_SX300.jpg", "DVD": "26 Jan 1999", "Language": "English", "imdbID": "tt0085244", "Title": "The Big Chill", "Genre": "Comedy, Drama", "Awards": "Nominated for 3 Oscars. Another 3 wins & 5 nominations.", "imdbVotes": "28,720", "Released": "30 Sep 1983", "Metascore": "62", "Runtime": "105 min", "Actors": "Tom Berenger, Glenn Close, Jeff Goldblum, William Hurt", "Writer": "Lawrence Kasdan, Barbara Benedek", "Ratings": [{"Source": "Internet Movie Database", "Value": "7.2/10"}, {"Source": "Rotten Tomatoes", "Value": "68%"}, {"Source": "Metacritic", "Value": "62/100"}]}