{"Plot": "Peggy Sue faints at a high school reunion. When she wakes up, she finds herself in her own past, just before she finished school.", "Country": "USA", "Response": "True", "Year": "1986", "BoxOffice": "N/A", "imdbRating": "6.3", "Director": "Francis Ford Coppola", "Type": "movie", "Production": "Twentieth Century Fox Home Entertainment", "Rated": "PG-13", "Website": "N/A", "Poster": "https://ia.media-imdb.com/images/M/MV5BYjg2MzE1MzQtZDY2My00YzU2LThjNmMtODY5YTU5ZDQ2MzAzXkEyXkFqcGdeQXVyMTA0MjU0Ng@@._V1_SX300.jpg", "DVD": "11 Aug 1998", "Language": "English", "imdbID": "tt0091738", "Title": "Peggy Sue Got Married", "Genre": "Comedy, Drama, Fantasy", "Awards": "Nominated for 3 Oscars. Another 3 wins & 9 nominations.", "imdbVotes": "29,242", "Released": "10 Oct 1986", "Metascore": "74", "Runtime": "103 min", "Actors": "Kathleen Turner, Nicolas Cage, Barry Miller, Catherine Hicks", "Writer": "Jerry Leichtling, Arlene Sarner", "Ratings": [{"Source": "Internet Movie Database", "Value": "6.3/10"}, {"Source": "Rotten Tomatoes", "Value": "85%"}, {"Source": "Metacritic", "Value": "74/100"}]}