{"DVD": "25 May 1999", "Runtime": "117 min", "Metascore": "N/A", "Writer": "David Mamet", "Language": "English", "Poster": "https://ia.media-imdb.com/images/M/MV5BOTU3MGE1OTgtM2YwNC00ODAyLTg3Y2YtYTM0NTc2ZTc3ZDFkL2ltYWdlXkEyXkFqcGdeQXVyNTAyODkwOQ@@._V1_SX300.jpg", "Country": "USA", "Director": "Lee Tamahori", "Type": "movie", "Title": "The Edge", "BoxOffice": "N/A", "Released": "26 Sep 1997", "Website": "N/A", "Genre": "Action, Adventure, Drama", "imdbID": "tt0119051", "Year": "1997", "Response": "True", "Actors": "Anthony Hopkins, Alec Baldwin, Elle Macpherson, Harold Perrineau", "Plot": "An intellectual billionaire and two lesser men struggle to band together and survive after getting stranded in the Alaskan wilderness with a blood-thirsty Kodiak Bear hunting them down.", "imdbRating": "6.9", "imdbVotes": "61,019", "Rated": "R", "Awards": "2 nominations.", "Ratings": [{"Value": "6.9/10", "Source": "Internet Movie Database"}, {"Value": "61%", "Source": "Rotten Tomatoes"}], "Production": "Fox"}