{"Type": "movie", "Response": "True", "imdbVotes": "215,179", "Poster": "https://m.media-amazon.com/images/M/MV5BMTQ4MzkzNjcxNV5BMl5BanBnXkFtZTcwNzk4NTU0Mg@@._V1_SX300.jpg", "Title": "Blade", "Released": "21 Aug 1998", "Language": "English, Russian", "Production": "New Line Cinema", "BoxOffice": "N/A", "Country": "USA", "Rated": "R", "Genre": "Action, Horror", "Runtime": "120 min", "Writer": "David S. Goyer", "imdbRating": "7.1", "Metascore": "45", "DVD": "22 Dec 1998", "Year": "1998", "Website": "N/A", "Actors": "Wesley Snipes, Stephen Dorff, Kris Kristofferson, N'Bushe Wright", "Awards": "4 wins & 8 nominations.", "Ratings": [{"Source": "Internet Movie Database", "Value": "7.1/10"}, {"Source": "Rotten Tomatoes", "Value": "54%"}, {"Source": "Metacritic", "Value": "45/100"}], "Director": "Stephen Norrington", "imdbID": "tt0120611", "Plot": "A half-vampire, half-mortal man becomes a protector of the mortal race, while slaying evil vampires."}