{"DVD": "16 Dec 1997", "Runtime": "93 min", "Metascore": "51", "Writer": "Kevin Eastman (characters), Peter Laird (characters), Bobby Herbeck (story), Todd W. Langen (screenplay), Bobby Herbeck (screenplay)", "Language": "English, French", "Poster": "https://m.media-amazon.com/images/M/MV5BNzg3NTQ4NDk5NV5BMl5BanBnXkFtZTgwNzMzNDg4NjE@._V1_SX300.jpg", "Country": "USA, Hong Kong", "Director": "Steve Barron", "Type": "movie", "Title": "Teenage Mutant Ninja Turtles", "BoxOffice": "N/A", "Released": "30 Mar 1990", "Website": "http://www.ninjaturtles.com/", "Genre": "Action, Adventure, Comedy", "imdbID": "tt0100758", "Year": "1990", "Response": "True", "Actors": "Judith Hoag, Elias Koteas, Josh Pais, David Forman", "Plot": "Four teenage mutant ninja turtles emerge from the shadows to protect New York City from a gang of criminal ninjas.", "imdbRating": "6.7", "imdbVotes": "75,587", "Rated": "PG", "Awards": "3 wins & 3 nominations.", "Ratings": [{"Value": "6.7/10", "Source": "Internet Movie Database"}, {"Value": "40%", "Source": "Rotten Tomatoes"}, {"Value": "51/100", "Source": "Metacritic"}], "Production": "New Line Cinema"}