{"Year": "1995", "Poster": "https://m.media-amazon.com/images/M/MV5BYmEwNjNlZTUtNzkwMS00ZTlhLTkyY2MtMjM2MzlmODQyZGVhXkEyXkFqcGdeQXVyNTI4MjkwNjA@._V1_SX300.jpg", "Website": "N/A", "Language": "English", "Released": "26 Apr 1995", "Production": "Zebra", "Rated": "R", "Response": "True", "Genre": "Comedy, Drama", "BoxOffice": "N/A", "Type": "movie", "Runtime": "91 min", "DVD": "10 Sep 2002", "Country": "USA", "Plot": "Two homies, Smokey and Craig, smoke a dope dealer's weed and try to figure a way to get the $200 they owe to the dealer by 10 p.m. that same night.", "Ratings": [{"Source": "Internet Movie Database", "Value": "7.3/10"}, {"Source": "Metacritic", "Value": "54/100"}], "Writer": "Ice Cube, DJ Pooh", "Title": "Friday", "Awards": "1 win & 5 nominations.", "imdbRating": "7.3", "Director": "F. Gary Gray", "imdbID": "tt0113118", "Actors": "Ice Cube, Chris Tucker, Nia Long, Tommy 'Tiny' Lister", "Metascore": "54", "imdbVotes": "86,169"}