{"Plot": "Two stumblebum inheritors are determined to rid their antique house of a mouse who is equally determined to stay where he is.", "Country": "USA", "Response": "True", "Year": "1997", "BoxOffice": "N/A", "imdbRating": "6.4", "Director": "Gore Verbinski", "Type": "movie", "Production": "Dreamworks", "Rated": "PG", "Website": "N/A", "Poster": "https://images-na.ssl-images-amazon.com/images/M/MV5BMzE0NTRhZWQtZmE5OS00NTI5LWJhMzMtMGU4MzE4MmRlZDE0L2ltYWdlL2ltYWdlXkEyXkFqcGdeQXVyMTQxNzMzNDI@._V1_SX300.jpg", "DVD": "01 Dec 1998", "Language": "English", "imdbID": "tt0119715", "Title": "Mousehunt", "Genre": "Comedy, Family", "Awards": "2 wins & 2 nominations.", "imdbVotes": "45,236", "Released": "19 Dec 1997", "Metascore": "54", "Runtime": "98 min", "Actors": "Nathan Lane, Lee Evans, Vicki Lewis, Maury Chaykin", "Writer": "Adam Rifkin", "Ratings": [{"Source": "Internet Movie Database", "Value": "6.4/10"}, {"Source": "Rotten Tomatoes", "Value": "42%"}, {"Source": "Metacritic", "Value": "54/100"}]}