{"Type": "movie", "Response": "True", "imdbVotes": "215,701", "Poster": "https://m.media-amazon.com/images/M/MV5BMzk2OTg4MTk1NF5BMl5BanBnXkFtZTcwNjExNTgzNA@@._V1_SX300.jpg", "Title": "GoldenEye", "Released": "17 Nov 1995", "Language": "English, Russian, Spanish", "Production": "MGM/UA", "BoxOffice": "N/A", "Country": "UK, USA", "Rated": "PG-13", "Genre": "Action, Adventure, Thriller", "Runtime": "130 min", "Writer": "Ian Fleming (characters), Michael France (story), Jeffrey Caine (screenplay), Bruce Feirstein (screenplay)", "imdbRating": "7.2", "Metascore": "65", "DVD": "19 Oct 1999", "Year": "1995", "Website": "N/A", "Actors": "Pierce Brosnan, Sean Bean, Izabella Scorupco, Famke Janssen", "Awards": "Nominated for 2 BAFTA Film Awards. Another 2 wins & 6 nominations.", "Ratings": [{"Source": "Internet Movie Database", "Value": "7.2/10"}, {"Source": "Rotten Tomatoes", "Value": "78%"}, {"Source": "Metacritic", "Value": "65/100"}], "Director": "Martin Campbell", "imdbID": "tt0113189", "Plot": "James Bond teams up with the lone survivor of a destroyed Russian research center to stop the hijacking of a nuclear space weapon by a fellow Agent formerly believed to be dead."}