{"Plot": "After an accident, a chauvinistic executive gains the ability to hear what women are really thinking.", "Country": "USA", "Response": "True", "Year": "2000", "BoxOffice": "$181,483,882", "imdbRating": "6.4", "Director": "Nancy Meyers", "Type": "movie", "Production": "Paramount Pictures", "Rated": "PG-13", "Website": "http://www.whatwomenwantmovie.com", "Poster": "https://m.media-amazon.com/images/M/MV5BZjUyZWE5YmMtNDA2ZC00NzFlLTg0MzktOTgzYjA2ZWE3NmIwXkEyXkFqcGdeQXVyNDk3NzU2MTQ@._V1_SX300.jpg", "DVD": "08 May 2001", "Language": "English, French", "imdbID": "tt0207201", "Title": "What Women Want", "Genre": "Comedy, Fantasy, Romance", "Awards": "Nominated for 1 Golden Globe. Another 5 wins & 8 nominations.", "imdbVotes": "174,607", "Released": "15 Dec 2000", "Metascore": "47", "Runtime": "127 min", "Actors": "Mel Gibson, Helen Hunt, Marisa Tomei, Alan Alda", "Writer": "Josh Goldsmith (story), Cathy Yuspa (story), Diane Drake (story), Josh Goldsmith (screenplay), Cathy Yuspa (screenplay)", "Ratings": [{"Source": "Internet Movie Database", "Value": "6.4/10"}, {"Source": "Rotten Tomatoes", "Value": "54%"}, {"Source": "Metacritic", "Value": "47/100"}]}