{"Language": "English, Serbo-Croatian", "Runtime": "130 min", "Production": "Miramax Films", "imdbID": "tt0247425", "Year": "2001", "Genre": "Crime, Drama", "Ratings": [{"Source": "Internet Movie Database", "Value": "7.4/10"}, {"Source": "Rotten Tomatoes", "Value": "93%"}, {"Source": "Metacritic", "Value": "86/100"}], "DVD": "13 Aug 2002", "imdbRating": "7.4", "Response": "True", "Type": "movie", "BoxOffice": "$35,733,119", "Released": "08 Feb 2002", "Website": "http://www.miramaxhighlights.com/inthebedroom/index.html", "Rated": "R", "Plot": "A New England couple's college-aged son dates an older woman who has two small children and an unwelcome ex-husband.", "Awards": "Nominated for 5 Oscars. Another 38 wins & 69 nominations.", "Poster": "https://m.media-amazon.com/images/M/MV5BYzQ3ZjhlMWItNGRmNS00OWQzLWJhYjEtMjA3NWIxNmZhNTFkXkEyXkFqcGdeQXVyMTQxNzMzNDI@._V1_SX300.jpg", "Title": "In the Bedroom", "Writer": "Andre Dubus (story \"Killings\"), Robert Festinger (screenplay), Todd Field (screenplay)", "Country": "USA", "Metascore": "86", "Actors": "Tom Wilkinson, Sissy Spacek, Nick Stahl, Marisa Tomei", "Director": "Todd Field", "imdbVotes": "34,520"}