{"Language": "English", "Runtime": "105 min", "Production": "N/A", "imdbID": "tt0313443", "Year": "2003", "Genre": "Crime, Drama, Mystery", "Ratings": [{"Source": "Internet Movie Database", "Value": "6.5/10"}, {"Source": "Metacritic", "Value": "63/100"}], "DVD": "08 Nov 2005", "imdbRating": "6.5", "Response": "True", "Type": "movie", "BoxOffice": "N/A", "Released": "03 Oct 2003", "Website": "N/A", "Rated": "PG-13", "Plot": "A Florida police chief must solve a vicious double homicide before he himself falls under suspicion.", "Awards": "4 wins & 7 nominations.", "Poster": "https://m.media-amazon.com/images/M/MV5BMjAxMTMzNTI5Ml5BMl5BanBnXkFtZTcwNDAwMTQ2NA@@._V1_SX300.jpg", "Title": "Out of Time", "Writer": "David Collard", "Country": "USA", "Metascore": "63", "Actors": "Denzel Washington, Eva Mendes, Sanaa Lathan, Dean Cain", "Director": "Carl Franklin", "imdbVotes": "50,754"}