{"Language": "English", "Rated": "PG", "Plot": "Sparks fly when spirited Elizabeth Bennet meets single, rich, and proud Mr. Darcy. But Mr. Darcy reluctantly finds himself falling in love with a woman beneath his class. Can each overcome their own pride and prejudice?", "imdbRating": "7.8", "DVD": "28 Feb 2006", "Genre": "Drama, Romance", "Response": "True", "Writer": "Jane Austen (novel), Deborah Moggach (screenplay)", "Metascore": "82", "imdbID": "tt0414387", "Actors": "Keira Knightley, Talulah Riley, Rosamund Pike, Jena Malone", "Awards": "Nominated for 4 Oscars. Another 13 wins & 54 nominations.", "Poster": "https://m.media-amazon.com/images/M/MV5BMTA1NDQ3NTcyOTNeQTJeQWpwZ15BbWU3MDA0MzA4MzE@._V1_SX300.jpg", "Title": "Pride & Prejudice", "Year": "2005", "imdbVotes": "218,515", "Production": "Focus Features", "Director": "Joe Wright", "Released": "23 Nov 2005", "BoxOffice": "$38,251,759", "Runtime": "129 min", "Country": "France, UK, USA", "Type": "movie", "Ratings": [{"Value": "7.8/10", "Source": "Internet Movie Database"}, {"Value": "86%", "Source": "Rotten Tomatoes"}, {"Value": "82/100", "Source": "Metacritic"}], "Website": "http://www.prideandprejudicemovie.net/splash.html"}