{"DVD": "05 Oct 2010", "Runtime": "75 min", "Metascore": "81", "Writer": "Tomm Moore (original story), Fabrice Ziolkowski (screenplay)", "Language": "English, Irish", "Poster": "https://m.media-amazon.com/images/M/MV5BMjEzMjEzNTIzOF5BMl5BanBnXkFtZTcwMTg2MjAyMw@@._V1_SX300.jpg", "Country": "France, Belgium, Ireland", "Director": "Tomm Moore, Nora Twomey(co-director)", "Type": "movie", "Title": "The Secret of Kells", "BoxOffice": "&pound;686,383", "Released": "11 Feb 2009", "Website": "http://thesecretofkells.com/", "Genre": "Animation, Adventure, Family", "imdbID": "tt0485601", "Year": "2009", "Response": "True", "Actors": "Evan McGuire, Christen Mooney, Brendan Gleeson, Mick Lally", "Plot": "A young boy in a remote medieval outpost under siege from barbarian raids is beckoned to adventure when a celebrated master illuminator arrives with an ancient book, brimming with secret wisdom and powers.", "imdbRating": "7.7", "imdbVotes": "26,957", "Rated": "NOT RATED", "Awards": "Nominated for 1 Oscar. Another 7 wins & 5 nominations.", "Ratings": [{"Value": "7.7/10", "Source": "Internet Movie Database"}, {"Value": "91%", "Source": "Rotten Tomatoes"}, {"Value": "81/100", "Source": "Metacritic"}], "Production": "GKIDS"}