{"Writer": "Karen Leigh Hopkins, Jessie Nelson", "imdbID": "tt0490084", "Language": "English, Mandarin, Italian", "imdbVotes": "34,758", "imdbRating": "5.6", "Website": "http://www.becauseisaidsomovie.com", "Year": "2007", "Awards": "1 nomination.", "BoxOffice": "$42,640,890", "DVD": "08 May 2007", "Director": "Michael Lehmann", "Country": "USA", "Rated": "PG-13", "Metascore": "26", "Released": "02 Feb 2007", "Title": "Because I Said So", "Type": "movie", "Genre": "Comedy, Romance", "Response": "True", "Poster": "https://m.media-amazon.com/images/M/MV5BMjAyNjU4NTMzNl5BMl5BanBnXkFtZTcwNzk3NzI0MQ@@._V1_SX300.jpg", "Runtime": "102 min", "Ratings": [{"Source": "Internet Movie Database", "Value": "5.6/10"}, {"Source": "Rotten Tomatoes", "Value": "4%"}, {"Source": "Metacritic", "Value": "26/100"}], "Production": "Universal Pictures", "Plot": "A meddling mother tries to set her daughter up with the right man so her kid won't follow in her footsteps.", "Actors": "Diane Keaton, Mandy Moore, Gabriel Macht, Tom Everett Scott"}