{"Language": "English", "Runtime": "101 min", "Production": "Sony/Screen Gems", "imdbID": "tt0880578", "Year": "2008", "Genre": "Crime, Horror, Mystery", "Ratings": [{"Source": "Internet Movie Database", "Value": "6.2/10"}, {"Source": "Rotten Tomatoes", "Value": "16%"}, {"Source": "Metacritic", "Value": "32/100"}], "DVD": "13 May 2008", "imdbRating": "6.2", "Response": "True", "Type": "movie", "BoxOffice": "$28,687,835", "Released": "25 Jan 2008", "Website": "http://www.sonypictures.com/movies/untraceable/", "Rated": "R", "Plot": "FBI agent Jennifer Marsh is tasked with hunting down a seemingly untraceable serial killer who posts live videos of his victims on the Internet. As time runs out, the cat and mouse chase becomes more personal.", "Awards": "1 win.", "Poster": "https://m.media-amazon.com/images/M/MV5BMTYyNTcwODYzMF5BMl5BanBnXkFtZTcwNjMwMzU1MQ@@._V1_SX300.jpg", "Title": "Untraceable", "Writer": "Robert Fyvolent (screenplay), Mark Brinker (screenplay), Allison Burnett (screenplay), Robert Fyvolent (story), Mark Brinker (story)", "Country": "USA", "Metascore": "32", "Actors": "Diane Lane, Billy Burke, Colin Hanks, Joseph Cross", "Director": "Gregory Hoblit", "imdbVotes": "44,021"}