{"Language": "English, Russian", "Runtime": "137 min", "Production": "Summit Entertainment", "imdbID": "tt1014763", "Year": "2015", "Genre": "Crime, Drama, Thriller", "Ratings": [{"Source": "Internet Movie Database", "Value": "6.5/10"}, {"Source": "Rotten Tomatoes", "Value": "26%"}, {"Source": "Metacritic", "Value": "41/100"}], "DVD": "04 Aug 2015", "imdbRating": "6.5", "Response": "True", "Type": "movie", "BoxOffice": "$1,314,609", "Released": "17 Apr 2015", "Website": "http://www.child44film.com/", "Rated": "R", "Plot": "A disgraced member of the Russian military police investigates a series of child murders during the Stalin-era Soviet Union.", "Awards": "2 nominations.", "Poster": "https://ia.media-imdb.com/images/M/MV5BMTk1NTkxOTc5Nl5BMl5BanBnXkFtZTgwODI0NTg0NDE@._V1_SX300.jpg", "Title": "Child 44", "Writer": "Richard Price (screenplay), Tom Rob Smith (novel)", "Country": "Czech Republic, UK, USA, Russia", "Metascore": "41", "Actors": "Xavier Atkins, Mark Lewis Jones, Tom Hardy, Joel Kinnaman", "Director": "Daniel Espinosa", "imdbVotes": "54,220"}