{"Plot": "A ski vacation turns horrific for a group of medical students, as they find themselves confronted by an unimaginable menace: Nazi zombies.", "Country": "Norway", "Response": "True", "Year": "2009", "BoxOffice": "N/A", "imdbRating": "6.3", "Director": "Tommy Wirkola", "Type": "movie", "Production": "IFC", "Rated": "NOT RATED", "Website": "http://www.dodsno.no/", "Poster": "https://ia.media-imdb.com/images/M/MV5BMzZiM2FhOTUtZTE4My00ZDNlLWEyZWItZDBiNDFjZDk2MWE1XkEyXkFqcGdeQXVyMTQxNzMzNDI@._V1_SX300.jpg", "DVD": "23 Feb 2010", "Language": "Norwegian", "imdbID": "tt1278340", "Title": "Dead Snow", "Genre": "Comedy, Horror", "Awards": "1 win & 1 nomination.", "imdbVotes": "58,925", "Released": "09 Jan 2009", "Metascore": "61", "Runtime": "91 min", "Actors": "Vegar Hoel, Stig Frode Henriksen, Charlotte Frogner, Lasse Valdal", "Writer": "Tommy Wirkola, Stig Frode Henriksen", "Ratings": [{"Source": "Internet Movie Database", "Value": "6.3/10"}, {"Source": "Rotten Tomatoes", "Value": "68%"}, {"Source": "Metacritic", "Value": "61/100"}]}