{"DVD": "04 Nov 2014", "Runtime": "98 min", "Metascore": "47", "Writer": "Ryan J. Condal (screenplay by), Evan Spiliotopoulos (screenplay by), Steve Moore (based on Radical Comics' \"Hercules\" by)", "Language": "English", "Poster": "https://m.media-amazon.com/images/M/MV5BMTQ4ODA5MTA4OF5BMl5BanBnXkFtZTgwNjMyODM5MTE@._V1_SX300.jpg", "Country": "USA", "Director": "Brett Ratner", "Type": "movie", "Title": "Hercules", "BoxOffice": "$59,445,889", "Released": "25 Jul 2014", "Website": "http://www.mightyhercules.com/", "Genre": "Action, Adventure, Fantasy", "imdbID": "tt1267297", "Year": "2014", "Response": "True", "Actors": "Dwayne Johnson, Ian McShane, John Hurt, Rufus Sewell", "Plot": "Having endured his legendary twelve labors, Hercules, the Greek demigod, has his life as a sword-for-hire tested when the King of Thrace and his daughter seek his aid in defeating a tyrannical warlord.", "imdbRating": "6.0", "imdbVotes": "130,043", "Rated": "PG-13", "Awards": "2 nominations.", "Ratings": [{"Value": "6.0/10", "Source": "Internet Movie Database"}, {"Value": "59%", "Source": "Rotten Tomatoes"}, {"Value": "47/100", "Source": "Metacritic"}], "Production": "Paramount Pictures"}