{"DVD": "30 Nov 2012", "Runtime": "106 min", "Metascore": "58", "Writer": "Etan Cohen, Lowell Cunningham (based on the Malibu comic by)", "Language": "English, Ukrainian", "Poster": "https://m.media-amazon.com/images/M/MV5BMTU2NTYxODcwMF5BMl5BanBnXkFtZTcwNDk1NDY0Nw@@._V1_SX300.jpg", "Country": "USA", "Director": "Barry Sonnenfeld", "Type": "movie", "Title": "Men in Black 3", "BoxOffice": "$179,020,854", "Released": "25 May 2012", "Website": "http://www.meninblack.com/", "Genre": "Action, Adventure, Comedy", "imdbID": "tt1409024", "Year": "2012", "Response": "True", "Actors": "Will Smith, Tommy Lee Jones, Josh Brolin, Jemaine Clement", "Plot": "Agent J travels in time to M.I.B.'s early days in 1969 to stop an alien from assassinating his friend Agent K and changing history.", "imdbRating": "6.8", "imdbVotes": "293,590", "Rated": "PG-13", "Awards": "1 win & 13 nominations.", "Ratings": [{"Value": "6.8/10", "Source": "Internet Movie Database"}, {"Value": "68%", "Source": "Rotten Tomatoes"}, {"Value": "58/100", "Source": "Metacritic"}], "Production": "Sony Pictures"}