{"Language": "Turkish", "Runtime": "140 min", "Production": "N/A", "imdbID": "tt1668191", "Year": "2010", "Genre": "Crime, Drama, Mystery", "Ratings": [{"Source": "Internet Movie Database", "Value": "7.5/10"}], "DVD": "N/A", "imdbRating": "7.5", "Response": "True", "Type": "movie", "BoxOffice": "N/A", "Released": "03 Dec 2010", "Website": "N/A", "Rated": "N/A", "Plot": "The lives of three homicide detectives are turned upside-down during a murder investigation.", "Awards": "N/A", "Poster": "https://images-na.ssl-images-amazon.com/images/M/MV5BMTYzMjkzODk4Nl5BMl5BanBnXkFtZTcwOTYzODQxNA@@._V1_SX300.jpg", "Title": "Hunting Season", "Writer": "Yavuz Turgul", "Country": "Turkey", "Metascore": "N/A", "Actors": "Sener Sen, Cem Yilmaz, \u00c7etin Tekindor, Melisa S\u00f6zen", "Director": "Yavuz Turgul", "imdbVotes": "22,941"}