{"Plot": "Luke and Kate are coworkers at a brewery who spend their nights drinking and flirting heavily. One weekend away together with their significant others proves who really belongs together and who doesn't.", "Country": "USA", "Response": "True", "Year": "2013", "BoxOffice": "$200,000", "imdbRating": "6.1", "Director": "Joe Swanberg", "Type": "movie", "Production": "Magnolia Pictures", "Rated": "R", "Website": "http://www.magpictures.com/drinkingbuddies/", "Poster": "https://m.media-amazon.com/images/M/MV5BMjMwNDU1NzMzM15BMl5BanBnXkFtZTcwNTY3ODk1OQ@@._V1_SX300.jpg", "DVD": "03 Dec 2013", "Language": "English", "imdbID": "tt2265398", "Title": "Drinking Buddies", "Genre": "Comedy, Drama, Romance", "Awards": "1 win & 3 nominations.", "imdbVotes": "51,981", "Released": "25 Jul 2013", "Metascore": "71", "Runtime": "90 min", "Actors": "Olivia Wilde, Jake Johnson, Anna Kendrick, Ron Livingston", "Writer": "Joe Swanberg", "Ratings": [{"Source": "Internet Movie Database", "Value": "6.1/10"}, {"Source": "Rotten Tomatoes", "Value": "83%"}, {"Source": "Metacritic", "Value": "71/100"}]}