{"Type": "movie", "Response": "True", "imdbVotes": "105,265", "Poster": "https://m.media-amazon.com/images/M/MV5BMTUyNzgxNjg2M15BMl5BanBnXkFtZTgwMTY1NDI1NjE@._V1_SX300.jpg", "Title": "Kung Fu Panda 3", "Released": "29 Jan 2016", "Language": "English, Mandarin", "Production": "DreamWorks Animation", "BoxOffice": "$128,341,070", "Country": "China, USA", "Rated": "PG", "Genre": "Animation, Action, Adventure", "Runtime": "95 min", "Writer": "Jonathan Aibel, Glenn Berger", "imdbRating": "7.1", "Metascore": "66", "DVD": "28 Jun 2016", "Year": "2016", "Website": "https://www.facebook.com/kungfupanda", "Actors": "Jack Black, Bryan Cranston, Dustin Hoffman, Angelina Jolie", "Awards": "1 win & 10 nominations.", "Ratings": [{"Source": "Internet Movie Database", "Value": "7.1/10"}, {"Source": "Rotten Tomatoes", "Value": "86%"}, {"Source": "Metacritic", "Value": "66/100"}], "Director": "Alessandro Carloni, Jennifer Yuh Nelson", "imdbID": "tt2267968", "Plot": "Continuing his \"legendary adventures of awesomeness\", Po must face two hugely epic, but different threats: one supernatural and the other a little closer to his home."}