{"Language": "English, French", "Rated": "PG-13", "Plot": "A girl in a small town forms an unlikely bond with a recently-paralyzed man she's taking care of.", "imdbRating": "7.4", "DVD": "30 Aug 2016", "Genre": "Drama, Romance", "Response": "True", "Writer": "Jojo Moyes (based on the novel by), Jojo Moyes (screenplay by)", "Metascore": "51", "imdbID": "tt2674426", "Actors": "Sam Claflin, Vanessa Kirby, Emilia Clarke, Eileen Dunwoodie", "Awards": "6 wins & 6 nominations.", "Poster": "https://m.media-amazon.com/images/M/MV5BMTQ2NjE4NDE2NV5BMl5BanBnXkFtZTgwOTcwNDE5NzE@._V1_SX300.jpg", "Title": "Me Before You", "Year": "2016", "imdbVotes": "149,317", "Production": "Warner Bros. Pictures", "Director": "Thea Sharrock", "Released": "03 Jun 2016", "BoxOffice": "$56,228,651", "Runtime": "106 min", "Country": "UK, USA", "Type": "movie", "Ratings": [{"Value": "7.4/10", "Source": "Internet Movie Database"}, {"Value": "56%", "Source": "Rotten Tomatoes"}, {"Value": "51/100", "Source": "Metacritic"}], "Website": "http://mebeforeyoumovie.com"}